python_cheatsheet/__init__.py
python_cheatsheet/a.py
python_cheatsheet/b.py
python_cheatsheet/c.py
python_cheatsheet/cli.py
python_cheatsheet/d.py
python_cheatsheet/e.py
python_cheatsheet/f.py
python_cheatsheet/g.py
python_cheatsheet/h.py
python_cheatsheet/i.py
python_cheatsheet/j.py
python_cheatsheet/k.py
python_cheatsheet/l.py
python_cheatsheet/m.py
python_cheatsheet/n.py
python_cheatsheet/o.py
python_cheatsheet/p.py
python_cheatsheet/q.py
python_cheatsheet/r.py
python_cheatsheet/s.py
python_cheatsheet/t.py
python_cheatsheet/u.py
python_cheatsheet/v.py
python_cheatsheet/w.py
python_cheatsheet/x.py
python_cheatsheet/y.py
python_cheatsheet/z.py
python_cheatsheet-0.4.0.dist-info/METADATA
python_cheatsheet-0.4.0.dist-info/RECORD
python_cheatsheet-0.4.0.dist-info/WHEEL
python_cheatsheet-0.4.0.dist-info/entry_points.txt
python_cheatsheet-0.4.0.dist-info/top_level.txt
