Metadata-Version: 2.1
Name: python-cheatsheet
Version: 0.4.0
Summary: A-Z Python Cheatsheet
Home-page: https://github.com/davewd/python_cheatsheet
Author: David Dawson
Author-email: davedawson.co@gmail.com
License: MIT license
Keywords: python_cheatsheet
Platform: UNKNOWN
Classifier: Development Status :: 2 - Pre-Alpha
Classifier: Intended Audience :: Developers
Classifier: License :: OSI Approved :: MIT License
Classifier: Natural Language :: English
Classifier: Programming Language :: Python :: 2
Classifier: Programming Language :: Python :: 2.7
Classifier: Programming Language :: Python :: 3
Classifier: Programming Language :: Python :: 3.4
Classifier: Programming Language :: Python :: 3.5
Classifier: Programming Language :: Python :: 3.6
Classifier: Programming Language :: Python :: 3.7
Requires-Dist: Click (>=6.0)
